makerbot/__init__.py
makerbot/__main__.py
makerbot/core.py
makerbot/helpers.py
nash_makerbot-0.1.5.dist-info/LICENSE
nash_makerbot-0.1.5.dist-info/METADATA
nash_makerbot-0.1.5.dist-info/WHEEL
nash_makerbot-0.1.5.dist-info/entry_points.txt
nash_makerbot-0.1.5.dist-info/top_level.txt
nash_makerbot-0.1.5.dist-info/RECORD
