Metadata-Version: 2.1
Name: nash-makerbot
Version: 0.1.5
Summary: A crypto market maker bot that is easy understand and customize
Home-page: https://gitlab.com/nash-io-public/nash-makerbot
Author: Nash
Author-email: contact@nash.io
License: MIT license
Keywords: nash,ethereum,neo,hft,bot,trading,market,maker
Platform: UNKNOWN
Classifier: Development Status :: 3 - Alpha
Classifier: Intended Audience :: Developers
Classifier: Natural Language :: English
Classifier: Programming Language :: Python :: 3
Classifier: Programming Language :: Python :: 3.7
Requires-Python: >=3.7
Requires-Dist: nash-api (==1.0.6)
Requires-Dist: numpy (==1.16.4)
Requires-Dist: pandas (==0.23.4)
Requires-Dist: docopt (==0.6.2)
